zapper/__init__.py
zapper/utils.py
zapper/zapper.py
zapper-0.0.1.dist-info/LICENSE
zapper-0.0.1.dist-info/METADATA
zapper-0.0.1.dist-info/WHEEL
zapper-0.0.1.dist-info/entry_points.txt
zapper-0.0.1.dist-info/top_level.txt
zapper-0.0.1.dist-info/RECORD
