Metadata-Version: 2.1
Name: zapper
Version: 0.0.1
Summary: Zapper is a utility to help download files concurrently
Home-page: https://github.com/abhinayy0/zapper.git
Author: Abhinay Yadav
Author-email: abhinayy0@gmail.com
License: UNKNOWN
Platform: UNKNOWN
Classifier: License :: OSI Approved :: MIT License
Classifier: Programming Language :: Python :: 3
Classifier: Programming Language :: Python :: 3.7
Requires-Dist: Click
Requires-Dist: requests
